src/__init__.py
src/main.py
src/proj.py
src/utils.py
m05_miniproject_MaryamLucas-0.0.1.dist-info/LICENSE.txt
m05_miniproject_MaryamLucas-0.0.1.dist-info/METADATA
m05_miniproject_MaryamLucas-0.0.1.dist-info/WHEEL
m05_miniproject_MaryamLucas-0.0.1.dist-info/entry_points.txt
m05_miniproject_MaryamLucas-0.0.1.dist-info/top_level.txt
m05_miniproject_MaryamLucas-0.0.1.dist-info/RECORD
