Metadata-Version: 2.1
Name: m05-miniproject-MaryamLucas
Version: 0.0.1
Summary: Example of a completely reproducible project !
Home-page: https://gitlab.idiap.ch/lstel/m05-naderi-stel
Author: Maryam Naderi & Lucas Stel
Author-email: maryam.naderi@idiap.ch
License: MIT license
Platform: UNKNOWN
Classifier: Development Status :: 4 - Beta
Classifier: Intended Audience :: Developers
Classifier: License :: OSI Approved :: BSD License
Classifier: Natural Language :: English
Classifier: Programming Language :: Python
Classifier: Programming Language :: Python :: 3
Classifier: Topic :: Software Development :: Libraries :: Python Modules
License-File: LICENSE.txt
Requires-Dist: numpy (==1.24.2)
Requires-Dist: pandas (==1.5.3)
Requires-Dist: scikit-learn (==1.2.2)
Requires-Dist: setuptools (==59.6.0)
